expit/__init__.py
expit/__main__.py
expit/core/__init__.py
expit/tests/__init__.py
expit/tests/test_easy.py
expit-1.0.13.dist-info/licenses/LICENSE.txt
expit-1.0.13.dist-info/METADATA
expit-1.0.13.dist-info/WHEEL
expit-1.0.13.dist-info/top_level.txt
expit-1.0.13.dist-info/RECORD
