Metadata-Version: 2.4
Name: expit
Version: 1.0.13
Summary: This project provides an implementation of the expit function.
Author-email: Johannes <johannes.programming@gmail.com>
License: The MIT License (MIT)
Project-URL: Download, https://pypi.org/project/expit/#files
Project-URL: Index, https://pypi.org/project/expit/
Project-URL: Source, https://github.com/johannes-programming/expit/
Project-URL: Website, https://expit.johannes-programming.online/
Classifier: Development Status :: 5 - Production/Stable
Classifier: License :: OSI Approved :: MIT License
Classifier: Natural Language :: English
Classifier: Operating System :: OS Independent
Classifier: Programming Language :: Python
Classifier: Programming Language :: Python :: 3
Classifier: Programming Language :: Python :: 3 :: Only
Classifier: Typing :: Typed
Requires-Python: >=3.11
License-File: LICENSE.txt
Requires-Dist: click>=8.1.7
Requires-Dist: preparse>=0.1.1
Dynamic: license-file
